datapak/__init__.py
datapak-0.0.1.dist-info/WHEEL
datapak-0.0.1.dist-info/METADATA
datapak-0.0.1.dist-info/RECORD
